{
  "title": "117 dead dogs found at California 'no-kill' animal rescue - many with gunshot wounds",
  "outlet": "BBC",
  "url": "https://news.google.com/rss/articles/CBMiWkFVX3lxTE5UaHBtX3VvSE1pRGM2NFUzQlFQZDNJcDdoakZZU3h0RkhIc1BvY0k4bGFfVXJaWWpBR3BrM0U3WVhYVy1oanV4ME1zYXJXeWltMHp5ZjFOc1IxZw?oc=5",
  "publishedDate": "2026-06-27",
  "summary": "Comprehensive up-to-date news coverage, aggregated from sources all over the world by Google News.",
  "campaignIds": [
    "sentience-statute"
  ],
  "topics": [
    "companion animals"
  ],
  "automated": true,
  "fetchedAt": "2026-07-15T08:38:22.578Z",
  "relevanceScore": 31,
  "reviewStatus": "review-needed"
}
